{"id": "067bf2ef", "status": "completed", "started_at": "2026-03-29T15:02:56.373140", "completed_at": "2026-03-29T15:09:46.349342", "product_id": "seese-pro-v9", "product_url": "https://seesepro.com/en-us/products/seese-pro-v9", "product_name": "Seese Pro™ Ultra-Light, Ultra-Powerful Blower", "config": {"angle": "testimonial", "structure": "pas", "persona": "Senior 55+", "tone": "conversational", "language": "en", "brief": "", "template": "founder-letter"}, "current_phase": "Done", "current_agent": "", "progress": 1.0, "error": "", "results": {"headline": "at-67-i-cleaned-my-entire-patio-in-4-minutes-without-asking", "qa_score": 0, "html_file": "data/output/067bf2ef/at-67-i-cleaned-my-entire-patio-in-4-minutes-without-asking.html", "thumbnail": "https://tempfile.aiquickdraw.com/image-format-converter/1774733602492-dd4s25vriv.jpg"}}